Metadata-Version: 1.1
Name: snaplogic-pymg
Version: 0.0.6
Summary: Like pymongo, but have cache logic on top to store a location or whatever
Home-page: UNKNOWN
Author: PassawitPunyawat
Author-email: passawit@punyawat.com
License: UNKNOWN
Keywords: HelloHello
Platform: UNKNOWN
Classifier: Intended Audience :: Education
Classifier: Programming Language :: Python :: 2
